fastfermion/__init__.py
fastfermion/_cirq.py
fastfermion/_of.py
fastfermion/_parse.py
fastfermion/ffcore.cp312-win_amd64.pyd
fastfermion-0.2.0.dist-info/licenses/LICENSE
fastfermion-0.2.0.dist-info/METADATA
fastfermion-0.2.0.dist-info/WHEEL
fastfermion-0.2.0.dist-info/top_level.txt
fastfermion-0.2.0.dist-info/RECORD
