Metadata-Version: 2.4
Name: fastfermion
Version: 0.2.0
Summary: A library for manipulating polynomials in Pauli, Fermi and Majorana operators.
Home-page: https://github.com/hfawzi/fastfermion
Author: Hamza Fawzi
Author-email: hamzafawzi@gmail.com
Requires-Python: >=3.10
License-File: LICENSE
Requires-Dist: scipy
Dynamic: author
Dynamic: author-email
Dynamic: description
Dynamic: description-content-type
Dynamic: home-page
Dynamic: license-file
Dynamic: requires-dist
Dynamic: requires-python
Dynamic: summary
